laituri/__init__.py
laituri/errors.py
laituri/py.typed
laituri/settings.py
laituri/types.py
laituri/docker/__init__.py
laituri/docker/credential_manager/__init__.py
laituri/docker/credential_manager/credential_managers.py
laituri/docker/credential_manager/docker_v1.py
laituri/docker/credential_manager/dummy.py
laituri/docker/credential_manager/ecr_with_role_v1.py
laituri/docker/credential_manager/errors.py
laituri/docker/credential_manager/registry_credentials_callback_v1.py
laituri/utils/__init__.py
laituri/utils/images.py
laituri/utils/retry.py
laituri-0.4.2.dist-info/LICENSE
laituri-0.4.2.dist-info/METADATA
laituri-0.4.2.dist-info/WHEEL
laituri-0.4.2.dist-info/top_level.txt
laituri-0.4.2.dist-info/RECORD
