Metadata-Version: 2.1
Name: laituri
Version: 0.4.2
Summary: Docker Toolkit for Python
Home-page: https://github.com/valohai/laituri
Author: Valohai
Author-email: hait@valohai.com
Maintainer: Ruksi Laine
Maintainer-email: me@ruk.si
License: MIT
Classifier: Programming Language :: Python :: 3
Classifier: License :: OSI Approved :: MIT License
Classifier: Operating System :: OS Independent
Requires-Python: >=3.7
License-File: LICENSE
Requires-Dist: requests (<3,>=2.23)
